safe_converter/__init__.py
safe_converter/converters.py
safe_converter/parser.py
tests/__init__.py
tests/test_parser.py
safe_converter-0.3.1.dist-info/LICENSE
safe_converter-0.3.1.dist-info/METADATA
safe_converter-0.3.1.dist-info/WHEEL
safe_converter-0.3.1.dist-info/top_level.txt
safe_converter-0.3.1.dist-info/RECORD
