Metadata-Version: 2.1
Name: safe_converter
Version: 0.3.1
Summary: Универсальный конвертор
Home-page: https://github.com/31iwnl/safe_converter
Author: 31
Author-email: xhispeco2018@gmail.com
Classifier: Programming Language :: Python :: 3
Classifier: License :: OSI Approved :: MIT License
Classifier: Operating System :: OS Independent
Requires-Python: >=3.6
License-File: LICENSE
